dinora/__init__.py
dinora/__main__.py
dinora/board_representation/canon_planes.py
dinora/cli.py
dinora/dataset.py
dinora/estimate_elo.py
dinora/keras_utils.py
dinora/model.py
dinora/net.py
dinora/policy.py
dinora/preprocess_pgn.py
dinora/search.py
dinora/selfplay.py
dinora/training.py
dinora/uci.py
dinora/utils.py
dinora-0.0.3.dist-info/entry_points.txt
dinora-0.0.3.dist-info/LICENSE
dinora-0.0.3.dist-info/WHEEL
dinora-0.0.3.dist-info/METADATA
dinora-0.0.3.dist-info/RECORD
