Metadata-Version: 2.1
Name: dinora
Version: 0.0.3
Summary: Dinora Chess Engine
Home-page: https://github.com/DinoraChess/dinora
License: GPL-3.0-only
Keywords: chess,uci,ai,tensorflow
Author: Saegl
Author-email: saegl@protonmail.com
Maintainer: Saegl
Maintainer-email: saegl@protonmail.com
Requires-Python: >=3.8,<3.11
Classifier: Development Status :: 3 - Alpha
Classifier: Environment :: GPU :: NVIDIA CUDA :: 11.2
Classifier: Intended Audience :: Developers
Classifier: Intended Audience :: Education
Classifier: Intended Audience :: End Users/Desktop
Classifier: Intended Audience :: Science/Research
Classifier: License :: OSI Approved :: GNU General Public License v3 (GPLv3)
Classifier: Programming Language :: Python :: 3
Classifier: Programming Language :: Python :: 3.8
Classifier: Programming Language :: Python :: 3.9
Classifier: Programming Language :: Python :: 3.10
Classifier: Topic :: Games/Entertainment :: Board Games
Classifier: Topic :: Scientific/Engineering :: Artificial Intelligence
Provides-Extra: tf
Requires-Dist: chess (>=1.6.1,<2.0.0)
Requires-Dist: click (>=8.1.3,<9.0.0)
Requires-Dist: numpy (>=1.19.2,<2.0.0)
Requires-Dist: protobuf (==3.20.1); extra == "tf"
Requires-Dist: pylru (>=1.2.0,<2.0.0)
Requires-Dist: tensorflow (==2.8.0); extra == "tf"
Project-URL: Documentation, https://dinora.readthedocs.io/en/latest
Project-URL: Repository, https://github.com/DinoraChess/dinora
